visioncam/__init__.py
visioncam/ablationcam.py
visioncam/base.py
visioncam/gradcam.py
visioncam/gradcamelementwise.py
visioncam/gradcamplusplus.py
visioncam/hirescam.py
visioncam/respondcam.py
visioncam/scorecam.py
visioncam/smoothgradcamplusplus.py
visioncam/xgradcam.py
visioncam-0.0.1.dist-info/LICENSE.txt
visioncam-0.0.1.dist-info/METADATA
visioncam-0.0.1.dist-info/WHEEL
visioncam-0.0.1.dist-info/top_level.txt
visioncam-0.0.1.dist-info/RECORD
